azure/mgmt/loadtestservice/__init__.py
azure/mgmt/loadtestservice/_configuration.py
azure/mgmt/loadtestservice/_load_test_mgmt_client.py
azure/mgmt/loadtestservice/_patch.py
azure/mgmt/loadtestservice/_serialization.py
azure/mgmt/loadtestservice/_vendor.py
azure/mgmt/loadtestservice/_version.py
azure/mgmt/loadtestservice/py.typed
azure/mgmt/loadtestservice/aio/__init__.py
azure/mgmt/loadtestservice/aio/_configuration.py
azure/mgmt/loadtestservice/aio/_load_test_mgmt_client.py
azure/mgmt/loadtestservice/aio/_patch.py
azure/mgmt/loadtestservice/aio/operations/__init__.py
azure/mgmt/loadtestservice/aio/operations/_load_tests_operations.py
azure/mgmt/loadtestservice/aio/operations/_operations.py
azure/mgmt/loadtestservice/aio/operations/_patch.py
azure/mgmt/loadtestservice/aio/operations/_quotas_operations.py
azure/mgmt/loadtestservice/models/__init__.py
azure/mgmt/loadtestservice/models/_load_test_mgmt_client_enums.py
azure/mgmt/loadtestservice/models/_models_py3.py
azure/mgmt/loadtestservice/models/_patch.py
azure/mgmt/loadtestservice/operations/__init__.py
azure/mgmt/loadtestservice/operations/_load_tests_operations.py
azure/mgmt/loadtestservice/operations/_operations.py
azure/mgmt/loadtestservice/operations/_patch.py
azure/mgmt/loadtestservice/operations/_quotas_operations.py
azure_mgmt_loadtestservice-1.0.0.dist-info/LICENSE
azure_mgmt_loadtestservice-1.0.0.dist-info/LICENSE.txt
azure_mgmt_loadtestservice-1.0.0.dist-info/METADATA
azure_mgmt_loadtestservice-1.0.0.dist-info/WHEEL
azure_mgmt_loadtestservice-1.0.0.dist-info/top_level.txt
azure_mgmt_loadtestservice-1.0.0.dist-info/RECORD
